Metadata-Version: 2.1
Name: EUDP
Version: 1.0.0
Summary: Encrypted UDP COmmUnicAtioN
Home-page: https://github.com/mastercodermerwin/EUDP
Author: Cactochan
License: UNKNOWN
Project-URL: Bug Tracker, https://github.com/mastercodermerwin/EUDP/issues
Platform: UNKNOWN
Classifier: Programming Language :: Python :: 3
Classifier: License :: OSI Approved :: MIT License
Classifier: Operating System :: OS Independent
License-File: LICENSE.txt
